feathertail-0.5.0.dist-info/METADATA
feathertail-0.5.0.dist-info/WHEEL
feathertail-0.5.0.dist-info/licenses/LICENSE
feathertail/__init__.py
feathertail/feathertail.cp312-win_amd64.pyd
feathertail-0.5.0.dist-info/RECORD
