Metadata-Version: 2.4
Name: feathertail
Version: 0.5.0
Classifier: Programming Language :: Python :: 3
Classifier: Programming Language :: Rust
Classifier: License :: OSI Approved :: MIT License
Classifier: Operating System :: OS Independent
License-File: LICENSE
Summary: A tiny, fast, Rust-backed transformation core for Python table data
Author-email: Odos Matthews <odosmatthews@gmail.com>
Requires-Python: >=3.8
